dingo/__init__.py
dingo/config/__init__.py
dingo/config/config.py
dingo/data/__init__.py
dingo/data/converter/__init__.py
dingo/data/converter/base.py
dingo/data/dataset/__init__.py
dingo/data/dataset/base.py
dingo/data/dataset/huggingface.py
dingo/data/dataset/local.py
dingo/data/dataset/spark.py
dingo/data/datasource/__init__.py
dingo/data/datasource/base.py
dingo/data/datasource/huggingface.py
dingo/data/datasource/local.py
dingo/data/datasource/s3.py
dingo/data/utils/__init__.py
dingo/data/utils/digit.py
dingo/data/utils/insecure_hash.py
dingo/exec/__init__.py
dingo/exec/base.py
dingo/exec/local.py
dingo/exec/spark.py
dingo/io/__init__.py
dingo/io/export.py
dingo/io/input.py
dingo/io/summary.py
dingo/model/__init__.py
dingo/model/model.py
dingo/model/modelres.py
dingo/model/llm/__init__.py
dingo/model/llm/base.py
dingo/model/llm/gpt.py
dingo/model/llm/kimi.py
dingo/model/llm/llama3.py
dingo/model/llm/perspective.py
dingo/model/llm/common/__init__.py
dingo/model/llm/common/base_llm.py
dingo/model/llm/common/base_llm_api.py
dingo/model/llm/common/openai_api.py
dingo/model/llm/common/turbomind_api.py
dingo/model/rule/__init__.py
dingo/model/rule/base.py
dingo/model/rule/common_rule.py
dingo/model/rule/image_rule.py
dingo/model/rule/prompt_rule.py
dingo/model/rule/util.py
dingo/utils/__init__.py
dingo/utils/log_util/__init__.py
dingo/utils/log_util/logger.py
evalu-1.0.2.1.dist-info/LICENSE
evalu-1.0.2.1.dist-info/METADATA
evalu-1.0.2.1.dist-info/WHEEL
evalu-1.0.2.1.dist-info/top_level.txt
evalu-1.0.2.1.dist-info/RECORD
