Metadata-Version: 2.1
Name: evalu
Version: 1.0.2.1
Summary: Language quality evaluation tool.
Home-page: https://github.com/shijinpjlab/Dingo/main
Author: SH AI Lab
Author-email: shailab@pjlab.org.cn
Classifier: Programming Language :: Python :: 3
Classifier: Operating System :: OS Independent
Requires-Python: >=3.10
License-File: LICENSE
Requires-Dist: hanziconv
Requires-Dist: jieba
Requires-Dist: jsonlines
Requires-Dist: langid
Requires-Dist: numpy
Requires-Dist: textstat
Requires-Dist: zhon
Requires-Dist: transformers
Requires-Dist: toml
Requires-Dist: pydantic
Requires-Dist: requests
Requires-Dist: Pillow ==9.4.0
Requires-Dist: opencv-python
Requires-Dist: nltk
Requires-Dist: datasets
Requires-Dist: chardet
Requires-Dist: packaging
Requires-Dist: pandas
Requires-Dist: fastapi
Requires-Dist: uvicorn
